predict/__init__.py
predict/model/README.md
predict/model/__init__.py
predict/model/model_components.py
prd_algorithms-0.1b0.dist-info/METADATA
prd_algorithms-0.1b0.dist-info/WHEEL
prd_algorithms-0.1b0.dist-info/RECORD
