Metadata-Version: 2.1
Name: prd-algorithms
Version: 0.1b0
Summary: Opta-Predict Algorithms Hub is a Python 3.8 library designed to empower healthcare professionals with advanced data analysis, forecasting, and statistical modeling tools, enhancing the Opta-Predict ecosystem.
Author: Haxaire
Author-email: haxaire@opta-lp.com
Requires-Python: >=3.8,<4.0
Classifier: Programming Language :: Python :: 3
Classifier: Programming Language :: Python :: 3.8
Classifier: Programming Language :: Python :: 3.9
Classifier: Programming Language :: Python :: 3.10
Classifier: Programming Language :: Python :: 3.11
Requires-Dist: numpy (==1.23.5) ; python_version >= "3.8"
Requires-Dist: pandas (==1.5.2) ; python_version >= "3.8"
Requires-Dist: scikit-learn (==1.2.0) ; python_version >= "3.8"
